hamster_bridge/bridge.py
hamster_bridge/__init__.py
hamster_bridge/listeners/jira.py
hamster_bridge/listeners/redmine.py
hamster_bridge/listeners/__init__.py
hamster_bridge-0.5.0.dist-info/DESCRIPTION.rst
hamster_bridge-0.5.0.dist-info/entry_points.txt
hamster_bridge-0.5.0.dist-info/METADATA
hamster_bridge-0.5.0.dist-info/metadata.json
hamster_bridge-0.5.0.dist-info/RECORD
hamster_bridge-0.5.0.dist-info/top_level.txt
hamster_bridge-0.5.0.dist-info/WHEEL
