Metadata-Version: 2.0
Name: hamster-bridge
Version: 0.5.0
Summary: let your hamster log your work to your favorite bugtracker
Home-page: https://github.com/kraiz/hamster-bridge
Author: Lars Kreisz
Author-email: der.kraiz@gmail.com
License: MIT
Platform: UNKNOWN
Requires-Dist: jira (>=0.40)
Provides-Extra: redmine
Requires-Dist: python-redmine; extra == 'redmine'
